nlpprepkit/__init__.py
nlpprepkit/core/exceptions.py
nlpprepkit/core/utils.py
nlpprepkit/functions/__init__.py
nlpprepkit/functions/contractions.py
nlpprepkit/functions/normalization.py
nlpprepkit/functions/text_cleaning.py
nlpprepkit/pipeline/__init__.py
nlpprepkit/pipeline/pipeline.py
nlpprepkit-1.2.3.dist-info/licenses/LICENSE
nlpprepkit-1.2.3.dist-info/METADATA
nlpprepkit-1.2.3.dist-info/WHEEL
nlpprepkit-1.2.3.dist-info/top_level.txt
nlpprepkit-1.2.3.dist-info/RECORD
