Metadata-Version: 2.4
Name: nlpprepkit
Version: 1.2.3
Summary: Text Preprocessing Library
Author-email: vnniciusg <vnniciusg@gmail.com>
Project-URL: repository, https://github.com/vnniciusg/nlpprepkit
Requires-Python: >=3.11
License-File: LICENSE
Requires-Dist: setuptools-scm>=8.2.0
Requires-Dist: tqdm>=4.67.1
Provides-Extra: dev
Requires-Dist: pytest>=8.3.5; extra == "dev"
Requires-Dist: setuptools>=76.0.0; extra == "dev"
Requires-Dist: setuptools-scm<8.2.1,>=8.0.0; extra == "dev"
Dynamic: license-file
